LICENSE
MANIFEST.in
README.md
setup.py
django_mutex_event.egg-info/PKG-INFO
django_mutex_event.egg-info/SOURCES.txt
django_mutex_event.egg-info/dependency_links.txt
django_mutex_event.egg-info/not-zip-safe
django_mutex_event.egg-info/requires.txt
django_mutex_event.egg-info/top_level.txt
dmutex/__init__.py
dmutex/debug.py
dmutex/models.py
tests/__init__.py
tests/models.py
tests/tests.py
tests/tests_base.py
tests/tests_meta.py