Metadata-Version: 1.1
Name: django-mutex-event
Version: 0.1.3
Summary: Mutual excluded events.
Home-page: http://lovasb.com
Author: Lovas Bence
Author-email: me@lovasb.com
License: MIT
Keywords: django,mutex-event,mutual exclusion
Platform: UNKNOWN
Classifier: Programming Language :: Python
Classifier: Topic :: Software Development :: Libraries :: Python Modules
Classifier: Framework :: Django
Classifier: Environment :: Web Environment
Classifier: Operating System :: OS Independent
Classifier: Natural Language :: English
